MANIFEST.in
README.rst
setup.py
anyblok_furetui/__init__.py
anyblok_furetui/conftest.py
anyblok_furetui/release.py
anyblok_furetui/security.py
anyblok_furetui.egg-info/PKG-INFO
anyblok_furetui.egg-info/SOURCES.txt
anyblok_furetui.egg-info/dependency_links.txt
anyblok_furetui.egg-info/entry_points.txt
anyblok_furetui.egg-info/not-zip-safe
anyblok_furetui.egg-info/requires.txt
anyblok_furetui.egg-info/top_level.txt
anyblok_furetui/auth/__init__.py
anyblok_furetui/auth/pyramid.py
anyblok_furetui/auth/user.py
anyblok_furetui/auth/data/menus.xml
anyblok_furetui/auth/data/resources.xml
anyblok_furetui/auth/data/spaces.xml
anyblok_furetui/auth/i18n/__init__.py
anyblok_furetui/auth/i18n/en.py
anyblok_furetui/auth/i18n/fr.py
anyblok_furetui/furetui/CODE.rst
anyblok_furetui/furetui/README.rst
anyblok_furetui/furetui/__init__.py
anyblok_furetui/furetui/core.py
anyblok_furetui/furetui/crud.py
anyblok_furetui/furetui/furetui.py
anyblok_furetui/furetui/menus.py
anyblok_furetui/furetui/pyramid.py
anyblok_furetui/furetui/resource.py
anyblok_furetui/furetui/space.py
anyblok_furetui/furetui/template.py
anyblok_furetui/furetui/i18n/__init__.py
anyblok_furetui/furetui/i18n/en.py
anyblok_furetui/furetui/i18n/fr.py
anyblok_furetui/furetui/tests/__init__.py
anyblok_furetui/furetui/tests/conftest.py
anyblok_furetui/furetui/tests/test_client.py
anyblok_furetui/furetui/tests/test_crud.py
anyblok_furetui/furetui/tests/test_template.py
anyblok_furetui/furetui/views/__init__.py
anyblok_furetui/furetui/views/call.py
anyblok_furetui/furetui/views/client.py
anyblok_furetui/furetui/views/crud.py
anyblok_furetui/furetui/views/resource.py
anyblok_furetui/furetui/views/space.py
anyblok_furetui/ip/__init__.py
anyblok_furetui/ip/furetui.py
anyblok_furetui/ip/tests/__init__.py
anyblok_furetui/ip/tests/conftest.py
anyblok_furetui/tests/__init__.py
anyblok_furetui/tests/test_many2many_crud.py
doc/BLOKS.rst
doc/CHANGES.rst
doc/FRONT.rst
doc/LICENSE.rst
doc/index.rst