Metadata-Version: 1.1
Name: anyblok-furetui
Version: 0.0.1
Summary: FuretUI for AnyBlok
Home-page: http://furetui.anyblok.org/0.0.1
Author: Jean-Sébastien Suzanne
Author-email: jssuzanne@anybox.fr
License: MPL2
Platform: UNKNOWN
Classifier: Development Status :: 5 - Production/Stable
Classifier: Intended Audience :: Developers
Classifier: Programming Language :: Python :: 3.5
Classifier: Programming Language :: Python :: 3.6
Classifier: Programming Language :: Python :: 3.7
Classifier: Programming Language :: Python :: 3.8
Classifier: Programming Language :: Python :: 3 :: Only
Classifier: Topic :: Software Development
Classifier: Topic :: Software Development :: Libraries :: Python Modules
Classifier: License :: OSI Approved :: Mozilla Public License 2.0 (MPL 2.0)
